{
  "project_info": {
    "project_number": "966903074302",
    "firebase_url": "https://playful-math-default-rtdb.firebaseio.com",
    "project_id": "playful-math",
    "storage_bucket": "playful-math.appspot.com"
  },
  "client": [
    {
      "client_info": {
        "mobilesdk_app_id": "1:966903074302:android:eca348c666dccb3d3b84af",
        "android_client_info": {
          "package_name": "com.example.playfulmath"
        }
      },
      "oauth_client": [
        {
          "client_id": "966903074302-14drvreb9lcfh3vjumdc3eqsioooijg8.apps.googleusercontent.com",
          "client_type": 3
        }
      ],
      "api_key": [
        {
          "current_key": "AIzaSyCtlRID_l9j_JxieyPq5saR8kqMtjYVTZk"
        }
      ],
      "services": {
        "appinvite_service": {
          "other_platform_oauth_client": [
            {
              "client_id": "966903074302-14drvreb9lcfh3vjumdc3eqsioooijg8.apps.googleusercontent.com",
              "client_type": 3
            }
          ]
        }
      }
    }
  ],
  "configuration_version": "1"
}